{"cameraMode":{"drawMode":0,"name":"Shaded","section":"Shading Mode"},"sceneLighting":false,"audioPlay":false,"sceneViewState":{"showFog":true,"showMaterialUpdate":false,"showSkybox":false,"showFlares":true,"showImageEffects":true,"showParticleSystems":true},"in2DMode":false,"pivot":{"x":4.30426025390625,"y":3.7960548400878908,"z":8.123043060302735},"rotation":{"x":-0.15545053780078889,"y":-0.8251408338546753,"z":0.27327120304107668,"w":-0.46939170360565188},"size":25.800357818603517,"orthographic":false}